{
    "Ar36": {
        "error": 0.7362275654964038,
        "error_type": "",
        "fit": "previous",
        "references": [
            {
                "exclude": false,
                "record_id": "bu-CC-N-2172"
            }
        ],
        "value": 83.42134282872684
    },
    "Ar37": {
        "error": 2.0873066836686014e-07,
        "error_type": "",
        "fit": "previous",
        "references": [
            {
                "exclude": false,
                "record_id": "bu-CC-N-2172"
            }
        ],
        "value": 6.509629154345333e-06
    },
    "Ar38": {
        "error": 3.626367788726796e-07,
        "error_type": "",
        "fit": "previous",
        "references": [
            {
                "exclude": false,
                "record_id": "bu-CC-N-2172"
            }
        ],
        "value": -3.9699047790154835e-07
    },
    "Ar39": {
        "error": 7.54514013471061e-07,
        "error_type": "",
        "fit": "previous",
        "references": [
            {
                "exclude": false,
                "record_id": "bu-CC-N-2172"
            }
        ],
        "value": -5.181305943595985e-07
    },
    "Ar40": {
        "error": 1.1546200271512903e-06,
        "error_type": "",
        "fit": "previous",
        "references": [
            {
                "exclude": false,
                "record_id": "bu-CC-N-2172"
            }
        ],
        "value": 5.7523182016607276e-05
    }
}